{
  "त्यस्तो": "tyesto",
  "सजाऊ": "sajaau",
  "हामीलाई": "hamilai",
  "आखिरमा": "aakhirma",
  "फक्रिएर": "fakriyera",
  "आँधीले": "aadhaile",
  "सकिँदैन": "sakidaina",
  "हृदय": "hryidaye",
  "बेहाल": "behaal",
  "गएर": "gayera",
  "बेग्लाबेग्लै": "beglabeglai",
  "धाउने": "dhaune",
  "निधक्क": "nidhakka",
  "अङ्गाली": "angaali",
  "छुने": "chune",
  "झुठो": "jhutho",
  "भन्छौं": "bhanchaun",
  "भाकी": "bhaki",
  "बत्ती": "batti",
  "केहि": "kehi",
  "चहनालाई": "chahanalai",
  "दिऊ": "diuu",
  "बसु": "basu",
  "गाउँछ": "gaaucha"
}
