{
  "तमाम": "tamam",
  "लाशको": "lashko",
  "मांसपिण्डको": "mansapindako",
  "आशमा": "aashma",
  "आँखाको": "aankhako",
  "द्यौन": "dhouna",
  "बैद्धमा": "baiddhama",
  "कोरेँ": "koren",
  "बसन्त": "basanta",
  "शुभ": "shubha",
  "बिछोड": "bichhod",
  "सकूँ": "sakun",
  "कैले": "kaile",
  "चल्दछ": "chaldachha",
  "मान": "maan",
  "आमा": "aama",
  "रेलमा": "relma",
  "आनी": "ani",
  "असफलता": "asafalta",
  "पौरुषताको": "pourushtako",
  "खेलेको": "kheleko",
  "लाग्ला": "lagla",
  "ओठमा": "oothma",
  "हाम्रै": "hamrai",
  "भन्छन्": "bhanchhan"
}
