{
  "भिज्ने": "bhijne",
  "छिचोली": "chhicholi",
  "गरेको": "gareko",
  "लाग्न": "lagna",
  "तप्किन": "tapkina",
  "खाँचो": "khacho",
  "बनि": "bani",
  "थोपा": "thopa",
  "माथिको": "mathiko",
  "एकादेशमा": "ekadeshma",
  "केटोले": "ketole",
  "बादलको": "badalko",
  "प्रतीक्षा": "pratiksha",
  "ठूला": "thula",
  "छेक्ने": "chhekne",
  "ल्याउने": "lyaune",
  "रोजूँ": "roju",
  "उति": "uti",
  "डुबिरहने": "dubirahane",
  "अजकल्टो": "ajkalto",
  "भयो": "bhayo",
  "खोजेर": "khojera",
  "भनूँ": "bharnu",
  "घाँस": "ghaans",
  "सृष्टिको": "sristiko"
}
